
[
    {
      "userId": "1",
      "name": "Shivani"
    },
    {
      "userId": "2",
      "name": "Krish"
    },
    {
      "userId": "3",
      "name": "Sathish"
    },
    {
      "userId": "4",
      "name": "Ramya"
    },
    {
      "userId": "5",
      "name": "Anu"
    },
    {
      "userId": "6",
      "name": "Sowmya"
    },
    {
      "userId": "7",
      "name": "Raj"
    },
    {
      "userId": "8",
      "name": "Vikram"
    },
    {
      "userId": "9",
      "name": "Kumar"
    },
    {
      "userId": "10",
      "name": "Shruthi"
    },
    {
      "userId": "11",
      "name": "Meena"
    },
    {
      "userId": "12",
      "name": "Brindha"
    },
    {
      "userId": "13",
      "name": "Ishwarya"
    },
    {
      "userId": "14",
      "name": "Hari"
    },
    {
      "userId": "15",
      "name": "Shankar"
    },
    {
      "userId": "16",
      "name": "Kriti"
    },
    {
      "userId": "17",
      "name": "Shradha"
    },
    {
      "userId": "18",
      "name": "Anaisha"
    },
    {
      "userId": "19",
      "name": "Nirup"
    },
    {
      "userId": "20",
      "name": "Karthik"
    }
]
  